SicpPythonMiaoshuZhongwenban/README.md
SicpPythonMiaoshuZhongwenban/__init__.py
SicpPythonMiaoshuZhongwenban/__main__.py
SicpPythonMiaoshuZhongwenban/file.epub
SicpPythonMiaoshuZhongwenban/index.html
SicpPythonMiaoshuZhongwenban/css/__init__.py
SicpPythonMiaoshuZhongwenban/css/annotations.css
SicpPythonMiaoshuZhongwenban/css/main.css
SicpPythonMiaoshuZhongwenban/css/normalize.css
SicpPythonMiaoshuZhongwenban/css/popup.css
SicpPythonMiaoshuZhongwenban/font/__init__.py
SicpPythonMiaoshuZhongwenban/font/fontello.eot
SicpPythonMiaoshuZhongwenban/font/fontello.svg
SicpPythonMiaoshuZhongwenban/font/fontello.ttf
SicpPythonMiaoshuZhongwenban/font/fontello.woff
SicpPythonMiaoshuZhongwenban/img/__init__.py
SicpPythonMiaoshuZhongwenban/img/annotator-glyph-sprite.png
SicpPythonMiaoshuZhongwenban/img/annotator-icon-sprite.png
SicpPythonMiaoshuZhongwenban/img/apple-touch-icon.png
SicpPythonMiaoshuZhongwenban/img/cancelfullscreen.png
SicpPythonMiaoshuZhongwenban/img/close.png
SicpPythonMiaoshuZhongwenban/img/fullscreen.png
SicpPythonMiaoshuZhongwenban/img/loader.gif
SicpPythonMiaoshuZhongwenban/img/menu-icon.png
SicpPythonMiaoshuZhongwenban/img/save.png
SicpPythonMiaoshuZhongwenban/img/saved.png
SicpPythonMiaoshuZhongwenban/img/settings-s.png
SicpPythonMiaoshuZhongwenban/img/settings.png
SicpPythonMiaoshuZhongwenban/img/star.png
SicpPythonMiaoshuZhongwenban/js/__init__.py
SicpPythonMiaoshuZhongwenban/js/epub.js
SicpPythonMiaoshuZhongwenban/js/epub.min.js
SicpPythonMiaoshuZhongwenban/js/epub.min.map
SicpPythonMiaoshuZhongwenban/js/hooks.min.js
SicpPythonMiaoshuZhongwenban/js/hooks.min.map
SicpPythonMiaoshuZhongwenban/js/reader.js
SicpPythonMiaoshuZhongwenban/js/reader.js.map
SicpPythonMiaoshuZhongwenban/js/reader.min.js
SicpPythonMiaoshuZhongwenban/js/reader.min.map
SicpPythonMiaoshuZhongwenban/js/hooks/__init__.py
SicpPythonMiaoshuZhongwenban/js/hooks/extensions/__init__.py
SicpPythonMiaoshuZhongwenban/js/hooks/extensions/highlight.js
sicp_python_miaoshu_zhongwenban-2024.3.2.0.dist-info/METADATA
sicp_python_miaoshu_zhongwenban-2024.3.2.0.dist-info/WHEEL
sicp_python_miaoshu_zhongwenban-2024.3.2.0.dist-info/entry_points.txt
sicp_python_miaoshu_zhongwenban-2024.3.2.0.dist-info/top_level.txt
sicp_python_miaoshu_zhongwenban-2024.3.2.0.dist-info/RECORD
